[
    {
        "id": "4201",
        "section": "colors",
        "name": "ألوان خشب دومز أصلى صناعة هندى 12 قلم طويل + براية",
        "desc": "ألوان خشب دومز أصلى صناعة هندى 12 قلم طويل + براية",
        "price": 70,
        "img": "https://raw.githubusercontent.com/3almsimsim/store/main/back-to-school/colors/images/doms-12shadesLong.jpg"
    },
    {
        "id": "4202",
        "section": "colors",
        "name": "ألوان خشب دومز أصلى صناعة هندى 12 قلم قصير + براية",
        "desc": "ألوان خشب دومز أصلى صناعة هندى 12 قلم قصير + براية",
        "price": 35,
        "img": "https://raw.githubusercontent.com/3almsimsim/store/main/back-to-school/colors/images/doms-12shadesShort.jpg"
    },
    {
        "id": "4203",
        "section": "colors",
        "name": "ألوان خشب دومز أصلى صناعة هندى 24 قلم طويل",
        "desc": "ألوان خشب دومز أصلى صناعة هندى 24 قلم طويل",
        "price": 150,
        "img": "https://raw.githubusercontent.com/3almsimsim/store/main/back-to-school/colors/images/doms-24shadesLong.jpg"
    },
    {
        "id": "4204",
        "section": "colors",
        "name": "ألوان خشب بريما 12 لون",
        "desc": "ألوان خشب بريما 12 لون",
        "price": 15,
        "img": "https://raw.githubusercontent.com/3almsimsim/store/main/back-to-school/colors/images/prima-12Short.jpg"
    },
    {
        "id": "4204",
        "section": "colors",
        "name": "ألوان خشب بريما 6 لون",
        "desc": "ألوان خشب بريما 6 لون",
        "price": 7.5,
        "img": "https://raw.githubusercontent.com/3almsimsim/store/main/back-to-school/colors/images/prima-6Short.jpg"
    }
    
]
